odoo/addons/l10n_it_delivery_note_customer_code/README.rst
odoo/addons/l10n_it_delivery_note_customer_code/__init__.py
odoo/addons/l10n_it_delivery_note_customer_code/__manifest__.py
odoo/addons/l10n_it_delivery_note_customer_code/i18n/it.po
odoo/addons/l10n_it_delivery_note_customer_code/i18n/l10n_it_delivery_note_customer_code.pot
odoo/addons/l10n_it_delivery_note_customer_code/models/__init__.py
odoo/addons/l10n_it_delivery_note_customer_code/models/delivery_note_line.py
odoo/addons/l10n_it_delivery_note_customer_code/readme/CONTRIBUTORS.rst
odoo/addons/l10n_it_delivery_note_customer_code/readme/DESCRIPTION.rst
odoo/addons/l10n_it_delivery_note_customer_code/report/report_delivery_note.xml
odoo/addons/l10n_it_delivery_note_customer_code/static/description/icon.png
odoo/addons/l10n_it_delivery_note_customer_code/static/description/index.html
odoo/addons/l10n_it_delivery_note_customer_code/views/stock_delivery_note_views.xml
odoo14_addon_l10n_it_delivery_note_customer_code-14.0.1.2.0.dist-info/METADATA
odoo14_addon_l10n_it_delivery_note_customer_code-14.0.1.2.0.dist-info/WHEEL
odoo14_addon_l10n_it_delivery_note_customer_code-14.0.1.2.0.dist-info/top_level.txt
odoo14_addon_l10n_it_delivery_note_customer_code-14.0.1.2.0.dist-info/RECORD
