Metadata-Version: 2.1
Name: odoo14-addon-l10n-it-delivery-note-customer-code
Version: 14.0.1.2.0
Summary: Product Customer code and name for delivery note
Home-page: https://github.com/OCA/l10n-italy
Author: Agile Business Group, Odoo Community Association (OCA)
Author-email: support@odoo-community.org
License: AGPL-3
Platform: UNKNOWN
Classifier: Programming Language :: Python
Classifier: Framework :: Odoo
Classifier: Framework :: Odoo :: 14.0
Classifier: License :: OSI Approved :: GNU Affero General Public License v3
Requires-Python: >=3.6
Requires-Dist: odoo14-addon-l10n-it-delivery-note
Requires-Dist: odoo14-addon-product-supplierinfo-for-customer-picking
Requires-Dist: odoo <14.1dev,>=14.0a
